Workbook
Name Slicer_Category: #N/A
Name Slicer_Channel: #N/A
Name Slicer_Region: #N/A

Sheet Raw Data
A1: Order ID | B1: Order Date | C1: Region | D1: Channel | E1: Salesperson | F1: Product | G1: Category | H1: Units | I1: Unit Price | J1: Revenue | K1: Cost | L1: Profit | M1: Profit Margin | N1: Month Start | O1: Month
A2: ORD0001 | B2: 45985 | C2: Gauteng | D2: Store | E2: A. Mokoena | F2: Wireless Headphones | G2: Electronics | H2: 4 | I2: 2925.69 | J2: =H2*I2 -> 11702.76 | K2: 7075.48 | L2: =J2-K2 -> 4627.28 | M2: =IFERROR(L2/J2,0) -> 0.39540074 | N2: =DATE(YEAR(B2),MONTH(B2),1) -> 45962 | O2: =TEXT(N2,"mmm") -> Nov
A3: ORD0002 | B3: 45673 | C3: Eastern Cape | D3: Online | E3: S. Jacobs | F3: Wireless Headphones | G3: Electronics | H3: 1 | I3: 2839.36 | J3: =H3*I3 -> 2839.36 | K3: 2134.76 | L3: =J3-K3 -> 704.6 | M3: =IFERROR(L3/J3,0) -> 0.24815451 | N3: =DATE(YEAR(B3),MONTH(B3),1) -> 45658 | O3: =TEXT(N3,"mmm") -> Jan
A4: ORD0003 | B4: 45959 | C4: KwaZulu-Natal | D4: Online | E4: A. Mokoena | F4: Ergonomic Chair | G4: Furniture | H4: 7 | I4: 8815.06 | J4: =H4*I4 -> 61705.42 | K4: 38091.69 | L4: =J4-K4 -> 23613.73 | M4: =IFERROR(L4/J4,0) -> 0.38268486 | N4: =DATE(YEAR(B4),MONTH(B4),1) -> 45931 | O4: =TEXT(N4,"mmm") -> Oct
A5: ORD0004 | B5: 45852 | C5: Gauteng | D5: Store | E5: A. Mokoena | F5: Wireless Headphones | G5: Electronics | H5: 5 | I5: 3945.32 | J5: =H5*I5 -> 19726.6 | K5: 14896.26 | L5: =J5-K5 -> 4830.34 | M5: =IFERROR(L5/J5,0) -> 0.24486429 | N5: =DATE(YEAR(B5),MONTH(B5),1) -> 45839 | O5: =TEXT(N5,"mmm") -> Jul
A6: ORD0005 | B6: 45940 | C6: Western Cape | D6: Store | E6: A. Mokoena | F6: Ergonomic Chair | G6: Furniture | H6: 4 | I6: 20088.61 | J6: =H6*I6 -> 80354.44 | K6: 47489.3 | L6: =J6-K6 -> 32865.14 | M6: =IFERROR(L6/J6,0) -> 0.40900217 | N6: =DATE(YEAR(B6),MONTH(B6),1) -> 45931 | O6: =TEXT(N6,"mmm") -> Oct
A7: ORD0006 | B7: 45777 | C7: KwaZulu-Natal | D7: Online | E7: N. Mthembu | F7: Wireless Headphones | G7: Electronics | H7: 6 | I7: 2962.65 | J7: =H7*I7 -> 17775.9 | K7: 11825.68 | L7: =J7-K7 -> 5950.22 | M7: =IFERROR(L7/J7,0) -> 0.33473523 | N7: =DATE(YEAR(B7),MONTH(B7),1) -> 45748 | O7: =TEXT(N7,"mmm") -> Apr
A8: ORD0007 | B8: 45983 | C8: Western Cape | D8: Store | E8: A. Mokoena | F8: Office Monitor 24 | G8: Electronics | H8: 8 | I8: 2834.96 | J8: =H8*I8 -> 22679.68 | K8: 18540.31 | L8: =J8-K8 -> 4139.37 | M8: =IFERROR(L8/J8,0) -> 0.18251448 | N8: =DATE(YEAR(B8),MONTH(B8),1) -> 45962 | O8: =TEXT(N8,"mmm") -> Nov
A9: ORD0008 | B9: 45775 | C9: KwaZulu-Natal | D9: Online | E9: S. Jacobs | F9: Laptop Pro 14 | G9: Electronics | H9: 2 | I9: 13349.04 | J9: =H9*I9 -> 26698.08 | K9: 21526.62 | L9: =J9-K9 -> 5171.46 | M9: =IFERROR(L9/J9,0) -> 0.19370157 | N9: =DATE(YEAR(B9),MONTH(B9),1) -> 45748 | O9: =TEXT(N9,"mmm") -> Apr
A10: ORD0009 | B10: 45860 | C10: Eastern Cape | D10: Store | E10: T. Dlamini | F10: Webcam HD | G10: Electronics | H10: 4 | I10: 411.21 | J10: =H10*I10 -> 1644.84 | K10: 1166.77 | L10: =J10-K10 -> 478.07 | M10: =IFERROR(L10/J10,0) -> 0.29064833 | N10: =DATE(YEAR(B10),MONTH(B10),1) -> 45839 | O10: =TEXT(N10,"mmm") -> Jul
A11: ORD0010 | B11: 45770 | C11: Western Cape | D11: Store | E11: N. Mthembu | F11: Office Monitor 24 | G11: Electronics | H11: 1 | I11: 5298.91 | J11: =H11*I11 -> 5298.91 | K11: 3267.74 | L11: =J11-K11 -> 2031.17 | M11: =IFERROR(L11/J11,0) -> 0.38331846 | N11: =DATE(YEAR(B11),MONTH(B11),1) -> 45748 | O11: =TEXT(N11,"mmm") -> Apr
A12: ORD0011 | B12: 45690 | C12: Gauteng | D12: Online | E12: N. Mthembu | F12: USB-C Hub | G12: Accessories | H12: 5 | I12: 865.52 | J12: =H12*I12 -> 4327.6 | K12: 3404.03 | L12: =J12-K12 -> 923.57 | M12: =IFERROR(L12/J12,0) -> 0.2134139 | N12: =DATE(YEAR(B12),MONTH(B12),1) -> 45689 | O12: =TEXT(N12,"mmm") -> Feb
A13: ORD0012 | B13: 45794 | C13: KwaZulu-Natal | D13: Online | E13: N. Mthembu | F13: Standing Desk | G13: Furniture | H13: 3 | I13: 10726.79 | J13: =H13*I13 -> 32180.37 | K13: 26031.21 | L13: =J13-K13 -> 6149.16 | M13: =IFERROR(L13/J13,0) -> 0.19108419 | N13: =DATE(YEAR(B13),MONTH(B13),1) -> 45778 | O13: =TEXT(N13,"mmm") -> May
... A601: ORD0600 | B601: 45929 | C601: Gauteng | D601: Store | E601: L. Naidoo | F601: USB-C Hub | G601: Accessories | H601: 8 | I601: 676 | J601: =H601*I601 -> 5408 | K601: 3861.51 | L601: =J601-K601 -> 1546.49 | M601: =IFERROR(L601/J601,0) -> 0.28596339 | N601: =DATE(YEAR(B601),MONTH(B601),1) -> 45901 | O601: =TEXT(N601,"mmm") -> Sep

Sheet Analysis
A1: Retail Sales Analysis
A2: Formula-driven analysis linked directly to Raw Data. Refresh/recalculate in Excel to update.
A4: Core KPIs
A5: =SUM('Raw Data'!$J$2:$J$601) -> 16007788 | C5: =SUM('Raw Data'!$L$2:$L$601) -> 4796641.8 | E5: =IFERROR(C5/A5,0) -> 0.29964426 | G5: =SUM('Raw Data'!$H$2:$H$601) -> 2747
A6: Total Revenue | C6: Total Profit | E6: Profit Margin | G6: Units Sold
A9: Monthly Performance
A10: Month | B10: Revenue | C10: Profit | D10: Units
A11: Jan | B11: =SUMIFS('Raw Data'!$J$2:$J$601,'Raw Data'!$O$2:$O$601,A11) -> 1313622.9 | C11: =SUMIFS('Raw Data'!$L$2:$L$601,'Raw Data'!$O$2:$O$601,A11) -> 386913.6 | D11: =SUMIFS('Raw Data'!$H$2:$H$601,'Raw Data'!$O$2:$O$601,A11) -> 196
A12: Feb | B12: =SUMIFS('Raw Data'!$J$2:$J$601,'Raw Data'!$O$2:$O$601,A12) -> 1036002.6 | C12: =SUMIFS('Raw Data'!$L$2:$L$601,'Raw Data'!$O$2:$O$601,A12) -> 331692.7 | D12: =SUMIFS('Raw Data'!$H$2:$H$601,'Raw Data'!$O$2:$O$601,A12) -> 206
A13: Mar | B13: =SUMIFS('Raw Data'!$J$2:$J$601,'Raw Data'!$O$2:$O$601,A13) -> 1189416.7 | C13: =SUMIFS('Raw Data'!$L$2:$L$601,'Raw Data'!$O$2:$O$601,A13) -> 358069.56 | D13: =SUMIFS('Raw Data'!$H$2:$H$601,'Raw Data'!$O$2:$O$601,A13) -> 229
A14: Apr | B14: =SUMIFS('Raw Data'!$J$2:$J$601,'Raw Data'!$O$2:$O$601,A14) -> 1359350.9 | C14: =SUMIFS('Raw Data'!$L$2:$L$601,'Raw Data'!$O$2:$O$601,A14) -> 447929.55 | D14: =SUMIFS('Raw Data'!$H$2:$H$601,'Raw Data'!$O$2:$O$601,A14) -> 208
A15: May | B15: =SUMIFS('Raw Data'!$J$2:$J$601,'Raw Data'!$O$2:$O$601,A15) -> 1640967.9 | C15: =SUMIFS('Raw Data'!$L$2:$L$601,'Raw Data'!$O$2:$O$601,A15) -> 470482.13 | D15: =SUMIFS('Raw Data'!$H$2:$H$601,'Raw Data'!$O$2:$O$601,A15) -> 316
A16: Jun | B16: =SUMIFS('Raw Data'!$J$2:$J$601,'Raw Data'!$O$2:$O$601,A16) -> 1303152.7 | C16: =SUMIFS('Raw Data'!$L$2:$L$601,'Raw Data'!$O$2:$O$601,A16) -> 403013.26 | D16: =SUMIFS('Raw Data'!$H$2:$H$601,'Raw Data'!$O$2:$O$601,A16) -> 212
A17: Jul | B17: =SUMIFS('Raw Data'!$J$2:$J$601,'Raw Data'!$O$2:$O$601,A17) -> 1716260.8 | C17: =SUMIFS('Raw Data'!$L$2:$L$601,'Raw Data'!$O$2:$O$601,A17) -> 511711.13 | D17: =SUMIFS('Raw Data'!$H$2:$H$601,'Raw Data'!$O$2:$O$601,A17) -> 262
A18: Aug | B18: =SUMIFS('Raw Data'!$J$2:$J$601,'Raw Data'!$O$2:$O$601,A18) -> 1260612.9 | C18: =SUMIFS('Raw Data'!$L$2:$L$601,'Raw Data'!$O$2:$O$601,A18) -> 351618.66 | D18: =SUMIFS('Raw Data'!$H$2:$H$601,'Raw Data'!$O$2:$O$601,A18) -> 226
A19: Sep | B19: =SUMIFS('Raw Data'!$J$2:$J$601,'Raw Data'!$O$2:$O$601,A19) -> 957721.95 | C19: =SUMIFS('Raw Data'!$L$2:$L$601,'Raw Data'!$O$2:$O$601,A19) -> 300083.88 | D19: =SUMIFS('Raw Data'!$H$2:$H$601,'Raw Data'!$O$2:$O$601,A19) -> 203
A20: Oct | B20: =SUMIFS('Raw Data'!$J$2:$J$601,'Raw Data'!$O$2:$O$601,A20) -> 1571618.3 | C20: =SUMIFS('Raw Data'!$L$2:$L$601,'Raw Data'!$O$2:$O$601,A20) -> 496842.44 | D20: =SUMIFS('Raw Data'!$H$2:$H$601,'Raw Data'!$O$2:$O$601,A20) -> 240
A21: Nov | B21: =SUMIFS('Raw Data'!$J$2:$J$601,'Raw Data'!$O$2:$O$601,A21) -> 1333713.8 | C21: =SUMIFS('Raw Data'!$L$2:$L$601,'Raw Data'!$O$2:$O$601,A21) -> 393796.13 | D21: =SUMIFS('Raw Data'!$H$2:$H$601,'Raw Data'!$O$2:$O$601,A21) -> 208
A22: Dec | B22: =SUMIFS('Raw Data'!$J$2:$J$601,'Raw Data'!$O$2:$O$601,A22) -> 1325346.4 | C22: =SUMIFS('Raw Data'!$L$2:$L$601,'Raw Data'!$O$2:$O$601,A22) -> 344488.72 | D22: =SUMIFS('Raw Data'!$H$2:$H$601,'Raw Data'!$O$2:$O$601,A22) -> 241
A25: Category Performance | F25: Regional Performance
A26: Category | B26: Revenue | C26: Profit | D26: Margin | F26: Region | G26: Revenue | H26: Profit | I26: Margin
A27: Electronics | B27: =SUMIFS('Raw Data'!$J$2:$J$601,'Raw Data'!$G$2:$G$601,A27) -> 6650110.7 | C27: =SUMIFS('Raw Data'!$L$2:$L$601,'Raw Data'!$G$2:$G$601,A27) -> 1995217.7 | D27: =IFERROR(C27/B27,0) -> 0.30002774 | F27: Gauteng | G27: =SUMIFS('Raw Data'!$J$2:$J$601,'Raw Data'!$C$2:$C$601,F27) -> 3544447.8 | H27: =SUMIFS('Raw Data'!$L$2:$L$601,'Raw Data'!$C$2:$C$601,F27) -> 1027623.4 | I27: =IFERROR(H27/G27,0) -> 0.28992484
A28: Accessories | B28: =SUMIFS('Raw Data'!$J$2:$J$601,'Raw Data'!$G$2:$G$601,A28) -> 880033.47 | C28: =SUMIFS('Raw Data'!$L$2:$L$601,'Raw Data'!$G$2:$G$601,A28) -> 269856.22 | D28: =IFERROR(C28/B28,0) -> 0.30664313 | F28: Western Cape | G28: =SUMIFS('Raw Data'!$J$2:$J$601,'Raw Data'!$C$2:$C$601,F28) -> 4131554.8 | H28: =SUMIFS('Raw Data'!$L$2:$L$601,'Raw Data'!$C$2:$C$601,F28) -> 1253666 | I28: =IFERROR(H28/G28,0) -> 0.30343685
A29: Furniture | B29: =SUMIFS('Raw Data'!$J$2:$J$601,'Raw Data'!$G$2:$G$601,A29) -> 8477643.7 | C29: =SUMIFS('Raw Data'!$L$2:$L$601,'Raw Data'!$G$2:$G$601,A29) -> 2531567.8 | D29: =IFERROR(C29/B29,0) -> 0.29861692 | F29: KwaZulu-Natal | G29: =SUMIFS('Raw Data'!$J$2:$J$601,'Raw Data'!$C$2:$C$601,F29) -> 3959103.2 | H29: =SUMIFS('Raw Data'!$L$2:$L$601,'Raw Data'!$C$2:$C$601,F29) -> 1256200.5 | I29: =IFERROR(H29/G29,0) -> 0.31729421
F30: Eastern Cape | G30: =SUMIFS('Raw Data'!$J$2:$J$601,'Raw Data'!$C$2:$C$601,F30) -> 4372682 | H30: =SUMIFS('Raw Data'!$L$2:$L$601,'Raw Data'!$C$2:$C$601,F30) -> 1259151.8 | I30: =IFERROR(H30/G30,0) -> 0.28795869

Sheet Dashboard
A1: Retail Sales Performance Dashboard
A2: 2025 sales performance | Excel analysis | recruiter-ready portfolio project
B4: =Analysis!A5 -> 16007788 | D4: =Analysis!C5 -> 4796641.8 | F4: =Analysis!E5 -> 0.29964426 | H4: =Analysis!G5 -> 2747
B5: Total Revenue | D5: Total Profit | F5: Profit Margin | H5: Units Sold
G23: KEY BUSINESS INSIGHTS
G24: • Revenue and profit are tracked monthly to identify seasonality and performance changes.
G25: • Category performance highlights where sales volume and profitability are strongest.
G26: • Regional profit is compared across all four regions with a complete category range.
G27: • Management should investigate high-revenue/low-margin products before scaling promotional spend.

Sheet PivotTables
A3: Row Labels | B3: Sum of Profit | C3: Sum of Units | D3: Sum of Revenue | F3: Row Labels | G3: Sum of Revenue | H3: Sum of Profit | J3: Row Labels | K3: Sum of Revenue | L3: Sum of Profit
A4: Eastern Cape | B4: 1259151.8 | C4: 754 | D4: 4372682 | F4: Accessories | G4: 880033.47 | H4: 269856.22 | J4: Online | K4: 8138240 | L4: 2481607.7
A5: Gauteng | B5: 1027623.4 | C5: 641 | D5: 3544447.8 | F5: Electronics | G5: 6650110.7 | H5: 1995217.7 | J5: Store | K5: 7869547.9 | L5: 2315034.1
A6: KwaZulu-Natal | B6: 1256200.5 | C6: 656 | D6: 3959103.2 | F6: Furniture | G6: 8477643.7 | H6: 2531567.8 | J6: Grand Total | K6: 16007788 | L6: 4796641.8
A7: Western Cape | B7: 1253666 | C7: 696 | D7: 4131554.8 | F7: Grand Total | G7: 16007788 | H7: 4796641.8
A8: Grand Total | B8: 4796641.8 | C8: 2747 | D8: 16007788
